<?xml version="1.0" encoding="UTF-8"?>
<mods:mods xmlns="http://www.loc.gov/mods/v3"
           xmlns:flvc="info:flvc/manifest/v1"
           xmlns:dcterms="http://purl.org/dc/terms/"
           xmlns:etd="http://www.ndltd.org/standards/metadata/etdms/1.0/"
           xmlns:mods="http://www.loc.gov/mods/v3"
           xmlns:xlink="http://www.w3.org/1999/xlink"
           xmlns:xsi="http://www.w3.org/2001/XMLSchema-instance"
           xsi:schemaLocation="http://www.loc.gov/mods/v3 http://www.loc.gov/standards/mods/v3/mods-3-4.xsd"
           version="3.4">
   <titleInfo  lang="eng">
      <title>Agreement between Parent and Teacher Ratings of Problem Behaviors</title>
      <subTitle>The Role of Children's Executive Function</subTitle>
   </titleInfo>
   <name  type="personal" authority="local">
      <namePart type="family">Osborne</namePart>
      <namePart type="given">Colleen M.</namePart>
      <affiliation>Theses and Dissertations</affiliation>
      <role>
         <roleTerm authority="local" type="text">author</roleTerm>
      </role>
   </name>
   <name 
         type="personal"
         authority="naf"
         authorityURI="http://id.loc.gov/authorities/names/"
         valueURI="http://id.loc.gov/authorities/names/n2012045221">
      <namePart type="family">Lonigan</namePart>
      <namePart type="given">Christopher J.</namePart>
      <role>
         <roleTerm authority="local" type="text">Professor Directing Thesis</roleTerm>
      </role>
   </name>
   <name 
         type="personal"
         authority="etd-naf"
         authorityURI="https://authorities.lib.fsu.edu/etd-naf/"
         valueURI="https://authorities.lib.fsu.edu/etd-naf/kofler">
      <namePart type="family">Kofler</namePart>
      <namePart type="given">Michael J.</namePart>
      <role>
         <roleTerm authority="local" type="text">Committee Member</roleTerm>
      </role>
   </name>
   <name 
         type="personal"
         authority="naf"
         authorityURI="http://id.loc.gov/authorities/names/"
         valueURI="http://id.loc.gov/authorities/names/n2009026723">
      <namePart type="family">Schatschneider</namePart>
      <namePart type="given">Christopher</namePart>
      <role>
         <roleTerm authority="local" type="text">Committee Member</roleTerm>
      </role>
   </name>
   <name 
         type="corporate"
         authority="naf"
         authorityURI="http://id.loc.gov/authorities/names/"
         valueURI="http://id.loc.gov/authorities/names/n80126238">
      <namePart>Florida State University</namePart>
      <role>
         <roleTerm authority="rda" type="text">degree granting institution</roleTerm>
      </role>
   </name>
   <name  type="corporate" authority="local">
      <namePart>College of Arts and Sciences</namePart>
      <role>
         <roleTerm authority="local" type="text">degree granting college</roleTerm>
      </role>
   </name>
   <name  type="corporate" authority="local">
      <namePart>Department of Psychology</namePart>
      <role>
         <roleTerm authority="local" type="text">degree granting department</roleTerm>
         <roleTerm authority="marcrelator" type="code">dgg</roleTerm>
      </role>
   </name>
   <typeOfResource >text</typeOfResource>
   <genre  authority="rdacontent">text</genre>
   <genre 
          authority="coar"
          authorityURI="http://purl.org/coar/resource_type"
          valueURI="http://purl.org/coar/resource_type/c_bdcc">master thesis</genre>
   <originInfo >
      <place>
         <placeTerm type="text">Tallahassee, Florida</placeTerm>
      </place>
      <dateIssued encoding="w3cdtf" keyDate="yes">2019</dateIssued>
      <publisher>Florida State University</publisher>
      <issuance>monographic</issuance>
   </originInfo>
   <language >
      <languageTerm type="text">English</languageTerm>
      <languageTerm type="code" authority="iso639-2b">eng</languageTerm>
   </language>
   <physicalDescription >
      <form authority="rdamedia" type="RDA media terms">computer</form>
      <form authority="rdacarrier" type="RDA carrier terms">online resource</form>
      <extent>1 online resource (68 pages)</extent>
      <digitalOrigin>born digital</digitalOrigin>
      <internetMediaType>application/pdf</internetMediaType>
   </physicalDescription>
   <abstract >Discrepancies between parent and teacher ratings of problem behaviors have been reported consistently throughout the literature. This study is built on the Attribution Bias Context Model, which suggests that the differences in the ratings of behavior may reflect different observable behaviors across contexts rather than different interpretations of the behavior by the informants. The purpose of this study was to examine the degree to which discrepancies in parents’ and teachers’ ratings of behaviors of young children were associated with children’s executive function (EF). Using a sample of 125 children attending first and second grade in North Florida, EF was directly assessed using a battery of EF measures that was developed for use with this age group, and both parents and teachers completed the Strengths and Weakness of ADHD-related and Normal Behavior (SWAN) questionnaire and Connors Teacher Rating Scale-15 (CTRS) to assess problem behaviors. Quantile regression was used to assess the changes in the relation of the discrepancy between parent and teacher ratings of externalizing problem behaviors and the children’s level of EF using a difference score for each subscale of both questionnaires. Although results from the SWAN inattention subscale were consistent with the hypothesis, results from other subscales and the CTRS were not consistent with the hypothesis. Scores for the Dimension Change Card Sorting (DCCS) task was significantly related to all of the difference scores except for both hyperactivity/impulsivity subscales.</abstract>
   <note  displayLabel="Submitted Note">A Thesis submitted to the Department of Psychology in partial fulfillment of the requirements for the degree of Master of Science.</note>
   <note  displayLabel="Degree Awarded">Spring Semester 2019.</note>
   <note  displayLabel="Date of Defense">March 6, 2019.</note>
   <note  displayLabel="Bibliography Note">Includes bibliographical references.</note>
   <note  displayLabel="Advisory Committee">Christopher J. Lonigan, Professor Directing Thesis; Michael Kofler, Committee Member; Christopher Schatschneider, Committee Member.</note>
   <subject 
            authority="lcsh"
            authorityURI="http://id.loc.gov/authorities/subjects/"
            valueURI="http://id.loc.gov/authorities/subjects/sh85027067">
      <topic>Clinical psychology</topic>
   </subject>
   <identifier  type="IID">2019_Spring_Osborne_fsu_0071N_15021</identifier>
   <extension >
      <etd:degree>
         <etd:name>Master of Science</etd:name>
         <etd:level>Masters</etd:level>
         <etd:discipline>Psychology</etd:discipline>
      </etd:degree>
      <flvc:flvc>
         <flvc:owningInstitution>FSU</flvc:owningInstitution>
         <flvc:submittingInstitution>FSU</flvc:submittingInstitution>
      </flvc:flvc>
   </extension>
   <recordInfo >
      <recordCreationDate encoding="w3cdtf">2019-10-14T16:36:31.241-04:00</recordCreationDate>
      <descriptionStandard>rda</descriptionStandard>
   </recordInfo>
</mods:mods>
