<?xml version="1.0" encoding="UTF-8"?>
<mods:mods xmlns="http://www.loc.gov/mods/v3"
           xmlns:flvc="info:flvc/manifest/v1"
           xmlns:dcterms="http://purl.org/dc/terms/"
           xmlns:etd="http://www.ndltd.org/standards/metadata/etdms/1.0/"
           xmlns:mods="http://www.loc.gov/mods/v3"
           xmlns:xlink="http://www.w3.org/1999/xlink"
           xmlns:xsi="http://www.w3.org/2001/XMLSchema-instance"
           xsi:schemaLocation="http://www.loc.gov/mods/v3 http://www.loc.gov/standards/mods/v3/mods-3-6.xsd"
           version="3.6">
   <titleInfo  lang="eng">
      <title>Turn It Up</title>
      <subTitle>Amplifying Historically Marginalized Students' Experiences with Interpersonal Conflict in the Residence Halls</subTitle>
   </titleInfo>
   <name  type="personal" authority="local">
      <nameIdentifier type="orcid" typeURI="https://orcid.org/">0009-0009-2463-2997</nameIdentifier>
      <namePart type="family">Blakesley</namePart>
      <namePart type="given">Rachel</namePart>
      <affiliation>Theses and Dissertations</affiliation>
      <role>
         <roleTerm authority="local" type="text">author</roleTerm>
      </role>
   </name>
   <name 
         type="personal"
         authority="naf"
         authorityURI="http://id.loc.gov/authorities/names/"
         valueURI="http://id.loc.gov/authorities/names/n2012007578">
      <namePart type="family">Jones</namePart>
      <namePart type="given">Tamara Bertrand</namePart>
      <affiliation>Theses and Dissertations</affiliation>
      <role>
         <roleTerm authority="local" type="text">professor directing dissertation</roleTerm>
      </role>
   </name>
   <name 
         type="personal"
         authority="etd-naf"
         authorityURI="https://authorities.lib.fsu.edu/etd-naf/"
         valueURI="https://authorities.lib.fsu.edu/etd-naf/lnjenkins">
      <namePart type="family">Jenkins</namePart>
      <namePart type="given">Lyndsay Nicole</namePart>
      <affiliation>Theses and Dissertations</affiliation>
      <role>
         <roleTerm authority="local" type="text">university representative</roleTerm>
      </role>
   </name>
   <name 
         type="personal"
         authority="etd-naf"
         authorityURI="https://authorities.lib.fsu.edu/etd-naf/"
         valueURI="https://authorities.lib.fsu.edu/etd-naf/szuilkowski">
      <namePart type="family">Zuilkowski</namePart>
      <namePart type="given">Stephanie Simmons</namePart>
      <affiliation>Theses and Dissertations</affiliation>
      <role>
         <roleTerm authority="local" type="text">committee member</roleTerm>
      </role>
   </name>
   <name 
         type="personal"
         authority="etd-naf"
         authorityURI="https://authorities.lib.fsu.edu/etd-naf/"
         valueURI="https://authorities.lib.fsu.edu/etd-naf/cmokher">
      <namePart type="family">Mokher</namePart>
      <namePart type="given">Christine G.</namePart>
      <affiliation>Theses and Dissertations</affiliation>
      <role>
         <roleTerm authority="local" type="text">committee member</roleTerm>
      </role>
   </name>
   <name 
         type="corporate"
         authority="naf"
         authorityURI="http://id.loc.gov/authorities/names/"
         valueURI="http://id.loc.gov/authorities/names/n80126238">
      <namePart>Florida State University</namePart>
      <role>
         <roleTerm authority="rda" type="text">degree granting institution</roleTerm>
      </role>
   </name>
   <name  type="corporate" authority="local">
      <namePart>College of Education, Health, and Human Sciences</namePart>
      <role>
         <roleTerm authority="local" type="text">degree granting college</roleTerm>
      </role>
   </name>
   <name  type="corporate" authority="local">
      <namePart>Department of Educational Leadership and Policy Studies</namePart>
      <role>
         <roleTerm authority="local" type="text">degree granting department</roleTerm>
         <roleTerm authority="marcrelator" type="code">dgg</roleTerm>
      </role>
   </name>
   <typeOfResource >text</typeOfResource>
   <genre  authority="rdacontent">text</genre>
   <genre 
          authority="coar"
          authorityURI="http://purl.org/coar/resource_type"
          valueURI="http://purl.org/coar/resource_type/c_db06">doctoral thesis</genre>
   <originInfo >
      <place>
         <placeTerm type="text">Tallahassee, Florida</placeTerm>
      </place>
      <dateIssued encoding="w3cdtf" keyDate="yes">2024</dateIssued>
      <publisher>Florida State University</publisher>
      <issuance>monographic</issuance>
   </originInfo>
   <language >
      <languageTerm type="text">English</languageTerm>
      <languageTerm type="code" authority="iso639-2b">eng</languageTerm>
   </language>
   <physicalDescription >
      <form authority="rdamedia" type="RDA media terms">computer</form>
      <form authority="rdacarrier" type="RDA carrier terms">online resource</form>
      <extent>1 online resource (131 pages)</extent>
      <digitalOrigin>born digital</digitalOrigin>
      <internetMediaType>application/pdf</internetMediaType>
   </physicalDescription>
   <abstract >Interpersonal conflict is inevitable as college students live together in residence halls with new and different people (Bresnahan et al., 2009; Ferguson &amp; Lareau, 2021; Fosnacht et al., 2020; Harwood et al., 2012; Morgan et al., 2019; Shook &amp; Fazio, 2008). Whether the conflict stems from small miscommunications to mismatched value systems, microaggressions, or bias, unresolved conflict can result in loss of sleep, lack of focus, a decreased sense of belonging, as well as lower retention and graduation rates (Acquah, 2016; Ferguson &amp; Lareau, 2021; Fosnacht et al., 2020; Hawken et al., 1991; McClain &amp; Perry, 2017; Morales, 2021; Sanchez et al., 2018). Traditional modes of conflict resolution prioritize White, middle-class norms and can impact first-generation and students of color more negatively at Historically White Institutions (HWIs) (Bresnahan et al., 2009; Chua &amp; Gudykunst, 1987; Ferguson &amp; Lareau, 2021; Hammer, 2005; Harwood et al., 2012; Wing &amp; Marya, 2013). The goal of this exploratory critical narrative inquiry (Merriam &amp; Tisdell, 2016) was to understand how first-generation, Pell-eligible, and students of color experience and manage interpersonal conflict in the residence halls at an HWI. Using participatory action research methods during a scaffolded, interactive focus group, the study's participants engaged in counterstorytelling, identified themes, and generated solutions to help students navigate future conflict more effectively (Baum et al., 2006; Delgado &amp; Stefancic, 2017; Fine et al., 2021; Martinez, 2020; Rutledge et al., 2021; Seaman, 2008). In this study, participants experienced interpersonal conflict and felt disrespected when others crossed cultural boundaries related to communication and community living. Only half of the participants communicated directly regarding the conflict, even fewer reached out for help, and only 25% of students were able to effectively resolve the conflict. Instead, participants utilized coping skills that prioritized relationships, as well as avoiding or deescalating the conflict. Participants desired deeper relationships with the students around them and intentional university strategies to build their confidence, communication, and relationship building skills. Additional recommendations included enhancing culturally responsive conflict resolution education for students and Resident Assistants, improving the roommate assignment and agreement processes, and utilizing personal outreach measures to boost the use of campus resources.</abstract>
   <note  displayLabel="Submitted Note">A Dissertation submitted to the Department of Educational Leadership and Policy Studies in partial fulfillment of the requirements for the degree of Doctor of Education.</note>
   <note  displayLabel="Date of Defense">March 1, 2024.</note>
   <note  displayLabel="Keywords">conflict resolution, first generation, housing, pell, residence life, students of color</note>
   <note  displayLabel="Bibliography Note">Includes bibliographical references.</note>
   <note  displayLabel="Advisory Committee">Tamara Bertrand Jones, Professor Directing Dissertation; Lyndsay Jenkins, University Representative; Stephanie Zuilkowski, Committee Member; Christine Mokher, Committee Member.</note>
   <subject 
            authority="lcsh"
            authorityURI="http://id.loc.gov/authorities/subjects/"
            valueURI="http://id.loc.gov/authorities/subjects/sh85041065">
      <topic>Education, Higher</topic>
   </subject>
   <identifier  type="IID">Blakesley_fsu_0071E_18672</identifier>
   <extension >
      <etd:degree>
         <etd:name>Doctor of Education</etd:name>
         <etd:level>Doctoral</etd:level>
         <etd:discipline>Educational Leadership and Policy Studies</etd:discipline>
      </etd:degree>
      <flvc:flvc>
         <flvc:owningInstitution>FSU</flvc:owningInstitution>
         <flvc:submittingInstitution>FSU</flvc:submittingInstitution>
      </flvc:flvc>
   </extension>
   <recordInfo >
      <recordCreationDate encoding="w3cdtf">2024-08-19T12:02:22.846834-04:00</recordCreationDate>
      <descriptionStandard>rda</descriptionStandard>
   </recordInfo>
</mods:mods>
