<?xml version="1.0" encoding="UTF-8" ?><!-- Created from PDF via Acrobat SaveAsXML --><!-- Mapping Table version: 28-February-2003 --><TaggedPDF-doc><?xpacket begin='﻿' id='W5M0MpCehiHzreSzNTczkc9d'?><?xpacket begin="﻿" id="W5M0MpCehiHzreSzNTczkc9d"?>
<x:xmpmeta xmlns:x="adobe:ns:meta/" x:xmptk="Adobe XMP Core 5.6-c016 91.163616, 2018/10/29-16:58:49        ">
   <rdf:RDF xmlns:rdf="http://www.w3.org/1999/02/22-rdf-syntax-ns#">
      <rdf:Description rdf:about=""
            xmlns:xmp="http://ns.adobe.com/xap/1.0/"
            xmlns:dc="http://purl.org/dc/elements/1.1/"
            xmlns:xmpMM="http://ns.adobe.com/xap/1.0/mm/"
            xmlns:pdf="http://ns.adobe.com/pdf/1.3/">
         <xmp:ModifyDate>2019-07-24T22:34:42-04:00</xmp:ModifyDate>
         <xmp:CreateDate>2019-07-24T22:34:41-04:00</xmp:CreateDate>
         <xmp:MetadataDate>2019-07-24T22:34:42-04:00</xmp:MetadataDate>
         <xmp:CreatorTool>Acrobat PDFMaker 19 for Word</xmp:CreatorTool>
         <dc:format>xml</dc:format>
         <dc:creator>
            <rdf:Seq>
               <rdf:li>NORCINI, JEFFREY</rdf:li>
            </rdf:Seq>
         </dc:creator>
         <xmpMM:DocumentID>uuid:396fd692-4c87-fc45-98a7-622b0f84eec5</xmpMM:DocumentID>
         <xmpMM:InstanceID>uuid:e69d3f63-1152-464e-8c0a-4a6e10ec57df</xmpMM:InstanceID>
         <pdf:Producer>Acrobat Pro DC 19 Paper Capture Plug-in</pdf:Producer>
      </rdf:Description>
   </rdf:RDF>
</x:xmpmeta>
                                                                                                    
                                                                                                    
                                                                                                    
                                                                                                    
                                                                                                    
                                                                                                    
                                                                                                    
                                                                                                    
                                                                                                    
                                                                                                    
                                                                                                    
                                                                                                    
                                                                                                    
                                                                                                    
                                                                                                    
                                                                                                    
                                                                                                    
                                                                                                    
                                                                                                    
                                                                                                    
                           
<?xpacket end="w"?><?xpacket end='r'?><P>FLORIDA STATE UNIVERSITY COLLEGE OF EDUCATION </P><P>DEVELOPING STRATEGY: AN EXAMINATION OF STRATEGIC PLANNING </P><P>PROCESSES OF DIVISIONS OF STUDENT AFFAIRS IN CANADIAN HIGHER </P><P>EDUCATION INSTITUTIONS </P><P>By </P><P>SHERMIN MURJI </P><P>A Dissertation submitted to the Department of Educational Leadership and Policy Studies in partial fulfillment of the requirements for the degree of Doctor of Philosophy </P><P>2019</P><P>Shermin Murji defended this Dissertation on April 11, 2019. The members of the supervisory committee were: </P><P>Tamara Bertrand Jones Professor Directing Dissertation </P><P>Bruce Lamont University Representative </P><P>Kathy L. Guthrie Committee Member </P><P>Robert A. Schwartz Committee Member </P><P>The Graduate School has verified and approved the above-named committee members and certifies that the Dissertation has been approved in accordance with university requirements. </P><P>ii </P></TaggedPDF-doc>