<?xml version="1.0" encoding="UTF-8" ?>
<!-- Created from PDF via Acrobat SaveAsXML -->
<!-- Mapping Table version: 28-February-2003 -->
<TaggedPDF-doc>
<?xpacket begin='﻿' id='W5M0MpCehiHzreSzNTczkc9d'?>
<?xpacket begin="﻿" id="W5M0MpCehiHzreSzNTczkc9d"?>
<x:xmpmeta xmlns:x="adobe:ns:meta/" x:xmptk="Adobe XMP Core 5.6-c017 91.164464, 2020/06/15-10:20:05        ">
   <rdf:RDF xmlns:rdf="http://www.w3.org/1999/02/22-rdf-syntax-ns#">
      <rdf:Description rdf:about=""
            xmlns:xmp="http://ns.adobe.com/xap/1.0/"
            xmlns:dc="http://purl.org/dc/elements/1.1/"
            xmlns:xmpMM="http://ns.adobe.com/xap/1.0/mm/"
            xmlns:pdf="http://ns.adobe.com/pdf/1.3/">
         <xmp:ModifyDate>2021-06-30T12:22:55-04:00</xmp:ModifyDate>
         <xmp:CreateDate>2021-06-30T12:22:54-04:00</xmp:CreateDate>
         <xmp:MetadataDate>2021-06-30T12:22:55-04:00</xmp:MetadataDate>
         <dc:format>xml</dc:format>
         <xmpMM:DocumentID>uuid:bdd1688d-a6a9-4715-9a7f-c8a4454d9ad1</xmpMM:DocumentID>
         <xmpMM:InstanceID>uuid:8bf1326e-4e66-4069-a942-5cc2e113c2f6</xmpMM:InstanceID>
         <pdf:Producer>Adobe Acrobat Pro DC (32-bit) 21 Paper Capture Plug-in</pdf:Producer>
      </rdf:Description>
   </rdf:RDF>
</x:xmpmeta>
                                                                                                    
                                                                                                    
                                                                                                    
                                                                                                    
                                                                                                    
                                                                                                    
                                                                                                    
                                                                                                    
                                                                                                    
                                                                                                    
                                                                                                    
                                                                                                    
                                                                                                    
                                                                                                    
                                                                                                    
                                                                                                    
                                                                                                    
                                                                                                    
                                                                                                    
                                                                                                    
                           
<?xpacket end="w"?>
<?xpacket end='r'?>

<P>FLORIDA STATE UNIVERSITY COLLEGE OF ARTS AND SCIENCES </P>

<P>DEVELOPMENT OF A NOVEL INTERVENTION FOR INTRUSIVE SUICIDAL </P>

<P>THOUGHTS INFORMED BY COGNITIVE BEHAVIORAL MODELS OF ANXIETY </P>

<P>By </P>

<P>JOSEPH W. BOFFA III </P>

<P>A Dissertation submitted to the Department of Psychology in partial fulfillment of the requirements for the degree of Doctor of Philosophy </P>

<P>2020 </P>

<P>© 2020 Joseph W. Boffa III </P>

<P>Joseph W. Boffa III defended this dissertation on April 27, 2020. The members of the supervisory committee were: </P>

<P>Norman B. Schmidt Professor Directing Dissertation </P>

<P>Mark D. Winegardner University Representative </P>

<P>Thomas E. Joiner Committee Member </P>

<P>Richard K. Wagner Committee Member </P>

<P>Jessica D. Riberio Committee Member </P>

<P>The Graduate School has verified and approved the above-named committee members, and certifies that the dissertation has been approved in accordance with university requirements. </P>

<P>ii </P>
</TaggedPDF-doc>
