<?xml version="1.0" encoding="UTF-8" ?>
<!-- Created from PDF via Acrobat SaveAsXML -->
<!-- Mapping Table version: 28-February-2003 -->
<TaggedPDF-doc>
<?xpacket begin='﻿' id='W5M0MpCehiHzreSzNTczkc9d'?>
<?xpacket begin="﻿" id="W5M0MpCehiHzreSzNTczkc9d"?>
<x:xmpmeta xmlns:x="adobe:ns:meta/" x:xmptk="Adobe XMP Core 9.1-c001 79.675d0f7, 2023/06/11-19:21:16        ">
   <rdf:RDF xmlns:rdf="http://www.w3.org/1999/02/22-rdf-syntax-ns#">
      <rdf:Description rdf:about=""
            xmlns:xmp="http://ns.adobe.com/xap/1.0/"
            xmlns:dc="http://purl.org/dc/elements/1.1/"
            xmlns:xmpMM="http://ns.adobe.com/xap/1.0/mm/"
            xmlns:pdf="http://ns.adobe.com/pdf/1.3/">
         <xmp:ModifyDate>2024-09-12T13:41:33-04:00</xmp:ModifyDate>
         <xmp:CreateDate>2024-09-12T13:41:33-04:00</xmp:CreateDate>
         <xmp:MetadataDate>2024-09-12T13:41:33-04:00</xmp:MetadataDate>
         <xmp:CreatorTool>Word</xmp:CreatorTool>
         <dc:format>xml</dc:format>
         <dc:title>
            <rdf:Alt>
               <rdf:li xml:lang="x-default">Microsoft Word - Berardo Dissertation 2024v2.docx</rdf:li>
            </rdf:Alt>
         </dc:title>
         <xmpMM:DocumentID>uuid:5e206240-ed77-4d08-a727-82b3735065eb</xmpMM:DocumentID>
         <xmpMM:InstanceID>uuid:c515bf1e-86f0-47bf-ae35-c05ec2212c42</xmpMM:InstanceID>
         <pdf:Producer>Adobe Acrobat Pro (32-bit) 24 Paper Capture Plug-in</pdf:Producer>
      </rdf:Description>
   </rdf:RDF>
</x:xmpmeta>
                                                                                                    
                                                                                                    
                                                                                                    
                                                                                                    
                                                                                                    
                                                                                                    
                                                                                                    
                                                                                                    
                                                                                                    
                                                                                                    
                                                                                                    
                                                                                                    
                                                                                                    
                                                                                                    
                                                                                                    
                                                                                                    
                                                                                                    
                                                                                                    
                                                                                                    
                                                                                                    
                           
<?xpacket end="w"?>
<?xpacket end='r'?>

<P>FLORIDA STATE UNIVERSITY </P>

<P>COLLEGE OF ARTS AND SCIENCES </P>

<P>SOCRATIC WISDOM IN THE </P>

<P>APOLOGY AND CHARMIDES </P>

<P>By </P>

<P>VINCENZA ANTONETTA BERARDO </P>

<P>A Dissertation submitted to the Department of Philosophy in partial fulfillment of the requirements for the degree of Doctor of Philosophy </P>

<P>2024 </P>

<P>© 2024 Vincenza Antonetta Berardo </P>

<P>Vincenza Antonetta Berardo defended this dissertation on June 7, 2024 The members of the supervisory committee were: </P>

<P>Nathanael Stein Professor Directing Dissertation </P>

<P>Svetoslava Slaveva-Griffin University Representative </P>

<P>Mark Lebar Committee Member </P>

<P>Jack Justus Committee Member </P>

<P>The Graduate School has verified and approved the above-named committee members, and certifies that the dissertation has been approved in accordance with university requirements. </P>

<P>ii </P>
</TaggedPDF-doc>
